{
	"dialogue": [
		{
			"sound": "",
			"speed": 0.05,
			"portrait": "bf",
			"boxState": "angry",
			"expression": "excited",
			"text": "Hey bitches, it's me boyfriend from Friday Night Funkin'"
		},
		{
			"sound": "",
			"speed": 0.05,
			"portrait": "bf",
			"boxState": "normal",
			"expression": "talk",
			"text": "I'm going to kick my clones ass..."
		},
		{
			"sound": "",
			"speed": 0.05,
			"portrait": "bf",
			"boxState": "angry",
			"expression": "excited",
			"text": "...in a SINGING BATTLE!!!"
		},
		{
			"sound": "",
			"speed": 0.05,
			"portrait": "gf",
			"boxState": "normal",
			"expression": "talk",
			"text": "You got this babe!"
		},
		{
			"sound": "",
			"speed": 0.05,
			"portrait": "",
			"boxState": "normal",
			"expression": "talk",
			"text": "Hell yeah, luv u <3"
		},
		{
			"sound": "",
			"speed": 0.05,
			"portrait": "gf",
			"boxState": "normal",
			"expression": "talk",
			"text": "Luv u too <3"
		},
		{
			"sound": "",
			"speed": 0.05,
			"portrait": "bf",
			"boxState": "normal",
			"expression": "talk",
			"text": "Ok this is getting a bit cringe, let's rap"
		}
	]
}